Metadata-Version: 1.0
Name: prob-GenGauBin-distributions
Version: 0.1
Summary: General, Gaussian, and Binomial distributions
Home-page: UNKNOWN
Author: Rajesh Atluri
Author-email: UNKNOWN
License: UNKNOWN
Platform: UNKNOWN
